me314/__init__.py
me314/me314.py
me314-0.0.1.dist-info/METADATA
me314-0.0.1.dist-info/WHEEL
me314-0.0.1.dist-info/top_level.txt
me314-0.0.1.dist-info/RECORD
