Metadata-Version: 2.1
Name: me314
Version: 0.0.1
Summary: Northwestern ME314 toolbox
Home-page: https://github.com/MuchenSun/me314
Author: Muchen Sun
License: UNKNOWN
Platform: UNKNOWN
Requires-Python: >=3.6
Requires-Dist: numpy
Requires-Dist: sympy
